botaxon/__init__.py
botaxon-0.2.dist-info/LICENSE
botaxon-0.2.dist-info/METADATA
botaxon-0.2.dist-info/WHEEL
botaxon-0.2.dist-info/top_level.txt
botaxon-0.2.dist-info/RECORD
